chabie/__init__.py
chabie/chabie.py
chabie/key.py
chabie-0.3.9.dist-info/LICENSE
chabie-0.3.9.dist-info/METADATA
chabie-0.3.9.dist-info/WHEEL
chabie-0.3.9.dist-info/top_level.txt
chabie-0.3.9.dist-info/RECORD
